{
    "page_url": "https://steamrip.com/bendy-and-the-dark-revival-free-download-h1/",
    "title": "Bendy and the Dark Revival Directly Download",
    "description": "Bendy and the Dark Revival is a first-person survival horror game and the much anticipated sequel to Bendy and the Ink Machine. Play as Audrey as she explores the depths of a curiously creepy animation studio thatâ€™s gone completely mad. Combat ink-tainted enemies, solve puzzles , and evade the ever-lurking Ink Demon while seeking your way back to the real world. You never know who or what is going to be around the next corner in this dilapidated realm of shadows and ink. Garfield Lasagna Party\nSCREENSHOTS SYSTEM REQUIREMENTS OS : Windows 10 (64 bit) Memory : 8 GB RAM Graphics : 2GB VRAM GeForce GTX 1030, AMD RX 550 DirectX : Version 11 Storage : 15 GB available space GAME INFO Genre: Action, Adventure Developer: Joey Drew Studios Platform: PC Game Size: 3.7 GB Released By: CODEX emu Version : v1.0.4.0332 | Full Version Pre-Installed Game MegaDB DOWNLOAD HERE",
    "screenshots": [
        "https://steamrip.com/wp-content/uploads/2022/11/bendy-and-the-dark-revival-steamrip.jpg",
        "https://steamrip.com/wp-content/uploads/2022/11/bendy-and-the-dark-revival-screenshots-steamrip.jpg"
    ],
    "system_requirements": {
        "OS": "Windows 10 (64 bit)",
        "Memory": "8 GB RAM",
        "Graphics": "2GB VRAM GeForce GTX 1030, AMD RX 550",
        "DirectX": "Version 11",
        "Storage": "15 GB available space"
    },
    "game_info": {
        "Genre": "Action, Adventure",
        "Developer": "Joey Drew Studios",
        "Platform": "PC",
        "Game Size": "3.7 GB",
        "Released By": "CODEX emu",
        "Version": "v1.0.4.0332 | Full",
        "Pre-Installed Game": ""
    },
    "download_links": [
        "https://megadb.net/qjo0t5zqgfuw"
    ],
    "cover_image": "https://steamrip.com/wp-content/uploads/2022/11/bendy-and-the-dark-revival-preinstalled-steamrip.jpg"
}