{
    "page_url": "https://steamrip.com/borderlands-the-pre-sequel-free-download/",
    "title": "Borderlands: The Pre-Sequel",
    "description": "Discover the story behind Borderlands 2 villain, Handsome Jack, and his rise to power. Taking place between the original Borderlands and Borderlands 2, the Pre-Sequel gives you a whole lotta new gameplay featuring the genre blending fusion of shooter and RPG mechanics that players have come to love.\nFloat through the air with each low gravity jump while taking enemies down from above using new ice and laser weapons. Catch-a-ride and explore the lunar landscape with new vehicles allowing for more levels of destructive mayhem.\nFeel the moon’s low gravity with every jump and stomp. Cause mayhem with new weapons equipped with ice and laser capabilities! New enemies offer a space-based twist! Witness Handsome Jack’s rise to power. Dive deep into the origins of iconic Borderlands villains. Turn the tables and experience Handsome Jack’s side of the story. Play as one of four new character classes, including Wilhelm the Enforcer, Nisha the Lawbringer, and Athena the Gladiator. Play as a combat-ready Claptrap prototype for the first-time! Experience the gray morality of working alongside Handsome Jack. SCREENSHOTS SYSTEM REQUIREMENTS OS *: Windows XP SP3 Processor: 2.4 GHz Dual Core Processor Memory: 2048 MB RAM Graphics: NVIDIA GeForce 8500 / ATI Radeon HD 2600 DirectX: Version 9.0 Storage: 13 GB available space Sound Card: DirectX 9 Compliant GAME INFO Genre: Action, RPG Developer: 2K Australia, Gearbox Software, Aspyr (Linux) Platform: PC Game Size: 18.8 GB Released By: Goldberg | Ty Owla, cs.rin.ru Version : Build 9212029 Pre-Installed Game GOFILE DOWNLOAD HERE Buzzheavier DOWNLOAD HERE",
    "screenshots": [
        "https://shared.cloudflare.steamstatic.com/store_item_assets/steam/apps/261640/ss_67fccbac39b495b4b8dfeac8456dfc9955495614.jpg",
        "https://shared.cloudflare.steamstatic.com/store_item_assets/steam/apps/261640/ss_a04737488d400bf8cc140c6b1a12b0e4aaeece5b.jpg",
        "https://shared.cloudflare.steamstatic.com/store_item_assets/steam/apps/261640/ss_a04737488d400bf8cc140c6b1a12b0e4aaeece5b.jpg",
        "https://gofile.io/d/iKvJCE",
        "https://buzzheavier.com/wdj6kp4adng2"
    ],
    "system_requirements": {
        "OS *": "Windows XP SP3",
        "Processor": "2.4 GHz Dual Core Processor",
        "Memory": "2048 MB RAM",
        "Graphics": "NVIDIA GeForce 8500 / ATI Radeon HD 2600",
        "DirectX": "Version 9.0",
        "Storage": "13 GB available space",
        "Sound Card": "DirectX 9 Compliant"
    },
    "game_info": {
        "Genre": "Action, RPG",
        "Developer": "2K Australia, Gearbox Software, Aspyr (Linux)",
        "Platform": "PC",
        "Game Size": "18.8 GB",
        "Released By": "Goldberg | Ty Owla, cs.rin.ru",
        "Version": "Build 9212029",
        "Pre-Installed Game": ""
    },
    "download_links": [
        "https://gofile.io/d/iKvJCE",
        "https://buzzheavier.com/wdj6kp4adng2"
    ],
    "cover_image": "https://steamrip.com/wp-content/uploads/2025/06/Borderlands-Pre-Sequel-featured.jpg"
}