{
    "page_url": "https://steamrip.com/ender-magnolia-bloom-in-the-mist-free-download/",
    "title": "ENDER MAGNOLIA Bloom in the Mist",
    "description": "Set in the Land of Fumes, this prosperous magical superpower is home to vast quantities of magical resources lurking underneath the surface. In hopes of advancing their kingdom’s development, artificial life forms known as Homunculi came into being. Regrettably, toxic Fumes from the underground drove the Homunculi to madness, turning them into feral monsters. Pesticide Not Required\nYou play as Lilac, an “Attuner” who possesses the power to save the Homunculi . Upon waking, you find yourself in a laboratory deep in the underground. There, you will become acquainted with the Homunculi closely involved in the kingdom’s downfall. Together with the Homunculi, set out in search of your lost memories and precious friends in the Land of Fumes. Follow the journey of destruction and rebirth in a post-apocalyptic world, decades after the disastrous Rain of Death .\nENDER MAGNOLIA is a dark fantasy 2D side-scrolling action RPG where you venture through the desolate Land of Fumes trying to save both humans and Homunculi. At the forefront of magical and mechanical development, the kingdom comprises of a hierarchical societal structure. Here, you’ll come across abandoned cities, discover laboratories oozing with heinous mysteries, a grand Sorcerer’s Academy, colossal factories, and much more. The hauntingly beautiful yet gruesome world of ENDER MAGNOLIA will unfold before you.\nJourney with Homunculi and help those who have lost their minds to the Fumes. Fight fearsome, powerful enemies, purify their souls, and rally your companions . Who will you save at the end of your quest — humans or Homunculi?\nSCREENSHOTS SYSTEM REQUIREMENTS OS : Windows 10 64 bit Processor : Dual Core @ 2.50Ghz Memory: 4 GB RAM Graphics : 1GB VRAM DirectX : Version 12 Storage: 2 GB available space GAME INFO Genre: Action, RPG Developer: Adglobe, Live Wire Platform: PC Game Size: 4.4 GB Released By: RUNE emu Version : v1.0.2-21654 [Build 17022604 | Full Version Pre-Installed Game MegaDB DOWNLOAD HERE",
    "screenshots": [
        "https://steamrip.com/wp-content/uploads/2024/03/ender-magnolia-bloom-in-the-mist-steamrip.jpg",
        "https://steamrip.com/wp-content/uploads/2024/03/ender-magnolia-bloom-in-the-mist-screenshots-steamrip.jpg"
    ],
    "system_requirements": {
        "OS": "Windows 10 64 bit",
        "Processor": "Dual Core @ 2.50Ghz",
        "Memory": "4 GB RAM",
        "Graphics": "1GB VRAM",
        "DirectX": "Version 12",
        "Storage": "2 GB available space"
    },
    "game_info": {
        "Genre": "Action, RPG",
        "Developer": "Adglobe, Live Wire",
        "Platform": "PC",
        "Game Size": "4.4 GB",
        "Released By": "RUNE emu",
        "Version": "v1.0.2-21654 [Build 17022604 | Full",
        "Pre-Installed Game": ""
    },
    "download_links": [
        "https://megadb.net/mz1hz4xy4xkw"
    ],
    "cover_image": "https://steamrip.com/wp-content/uploads/2024/03/ender-magnolia-bloom-in-the-mist-preinstalled-steamrip.jpg"
}