{
    "page_url": "https://steamrip.com/final-fantasy-type-0-hd-free-download/",
    "title": "Final Fantasy Type-0 HD",
    "description": "Step into the fray as Class Zero, a group of students from an elite military academy whose country is attacked by an aggressive neighbouring Empire. In the brutal and harrowing struggle that follows, defeat the Empire and uncover the secrets behind the war using a range of powerful magical and combat abilities and an exciting new battle system. [Chilla’s Art] The Closing Shift\nKey Features:\nSCREENSHOTS SYSTEM REQUIREMENTS OS *: Windows 10 64 Bit, Windows 8.1 64 Bit, Windows 8 64 Bit, Windows 7 64 Bit Service Pack 1 Processor: CPU Core i3 2.5GHz Memory: 4 GB RAM Graphics: GTX560Ti or AMD Radeon 7790 mp4 [H.264] DirectX: Version 11 Storage: 30 GB available space GAME INFO Genre: Action, RPG Developer: Square Enix Platform: PC Game Size: 24.7 GB Released By: Tenoke + Owla CSF, cs.rin.ru Version : Build 3301128 Pre-Installed Game GOFILE DOWNLOAD HERE Buzzheavier DOWNLOAD HERE",
    "screenshots": [
        "https://shared.fastly.steamstatic.com/store_item_assets/steam/apps/340170/ss_c312fc0074cd2728bed671bc1645b5fa467a3c9a.jpg",
        "https://shared.fastly.steamstatic.com/store_item_assets/steam/apps/340170/ss_f3f0d1925da2a4bc49cf1faed26b25aa1fc25766.jpg"
    ],
    "system_requirements": {
        "OS *": "Windows 10 64 Bit, Windows 8.1 64 Bit, Windows 8 64 Bit, Windows 7 64 Bit Service Pack 1",
        "Processor": "CPU Core i3 2.5GHz",
        "Memory": "4 GB RAM",
        "Graphics": "GTX560Ti or AMD Radeon 7790 mp4 [H.264]",
        "DirectX": "Version 11",
        "Storage": "30 GB available space"
    },
    "game_info": {
        "Genre": "Action, RPG",
        "Developer": "Square Enix",
        "Platform": "PC",
        "Game Size": "24.7 GB",
        "Released By": "Tenoke + Owla CSF, cs.rin.ru",
        "Version": "Build 3301128",
        "Pre-Installed Game": ""
    },
    "download_links": [
        "https://gofile.io/d/MW356G",
        "https://buzzheavier.com/hianyr78wjhi"
    ],
    "cover_image": "https://steamrip.com/wp-content/uploads/2025/06/header.jpg"
}