{
    "page_url": "https://steamrip.com/mindseye-free-download/",
    "title": "MindsEye",
    "description": "Welcome to Redrock\nWelcome to the world of MindsEye, a single-player, action-adventure thriller set in the fictional near future city of Redrock – an intense, super-heated, desert metropolis where technology is king. Apollo Justice: Ace Attorney Trilogy\nMan and Machine\nRobots carry out manual tasks and an algorithm connects all-seeing devices to make Redrock ‘The Safest City in the World’. It’s a living experiment in the existential potential of man and machine. As is the protagonist, Jacob Diaz, a former special-ops soldier haunted by fragmented memories from his MindsEye neural implant.\nFight Your Fate\nYou’ll play as Jacob as he fights to uncover his truth in a world where AI, hi-tech experimentation and unchecked military power shapes every encounter. What starts as a personal quest quickly becomes a mission that’s critical to all of humanity’s survival as sentient robots rise, propelled by human greed.\nCaught in the Crossfire\nCentral to the game’s tightly crafted narrative is the volatile relationship between the eccentric head of Silva Industries, Marco Silva and Redrock’s power-hungry mayor, Shiva Vega. Where billionaire Silva wants to change the course of human evolution, Vega wants greater control of his technology and Redrock’s citizens in the process.\nIntense Combat & Driving\nWith Jacob caught in the crossfire, get ready for explosive combat using an array of advanced weaponry in missions on foot, behind the wheel and in the air. MindsEye is a richly detailed thriller with best-in-class cinematics and a thought-provoking story about when technology and ambition collide.\nSCREENSHOTS SYSTEM REQUIREMENTS OS: Windows 10/11 64 Bit with latest updates Processor: Intel Core i5-12400F / AMD Ryzen 5 5600X Memory: 16 GB RAM Graphics: 6GB VRAM, Nvidia GeForce RTX 2060 / AMD Radeon RX 5600 XT DirectX: Version 12 Storage: 70 GB available space Additional Notes: SSD required GAME INFO Genre: Action, Adventure Developer: Build A Rocket Boy Platform: PC Game Size: 49.5 GB Released By: Rune | Ty InsaneRamZes Version : v4598223 | Build 18756131 Pre-Installed Game GOFILE DOWNLOAD HERE Buzzheavier DOWNLOAD HERE DataNodes DOWNLOAD HERE",
    "screenshots": [
        "https://shared.fastly.steamstatic.com/store_item_assets/steam/apps/257119522/7cb148ad797a4b0f8f6ad8a1721aefa7e436ee31/movie_232x130.jpg",
        "https://shared.fastly.steamstatic.com/store_item_assets/steam/apps/257097681/a4ffaa3674ba2fd36e96dd2119eff9f569f7f086/movie_232x130.jpg",
        "https://gofile.io/d/n3quv1",
        "https://buzzheavier.com/d7d52nav7a05",
        "https://datanodes.to/dctvu7bpl5w0/Mindseye-SteamRIP.com.rar"
    ],
    "system_requirements": {
        "OS": "Windows 10/11 64 Bit with latest updates",
        "Processor": "Intel Core i5-12400F / AMD Ryzen 5 5600X",
        "Memory": "16 GB RAM",
        "Graphics": "6GB VRAM, Nvidia GeForce RTX 2060 / AMD Radeon RX 5600 XT",
        "DirectX": "Version 12",
        "Storage": "70 GB available space",
        "Additional Notes": "SSD required"
    },
    "game_info": {
        "Genre": "Action, Adventure",
        "Developer": "Build A Rocket Boy",
        "Platform": "PC",
        "Game Size": "49.5 GB",
        "Released By": "Rune | Ty InsaneRamZes",
        "Version": "v4598223 | Build 18756131",
        "Pre-Installed Game": ""
    },
    "download_links": [
        "https://gofile.io/d/n3quv1",
        "https://buzzheavier.com/d7d52nav7a05",
        "https://datanodes.to/dctvu7bpl5w0/Mindseye-SteamRIP.com.rar"
    ],
    "cover_image": "https://steamrip.com/wp-content/uploads/2025/06/MindsEye_featured_final.jpg"
}