{
    "page_url": "https://steamrip.com/project-castaway-free-download/",
    "title": "Project Castaway",
    "description": "Project Castaway plunges you into the heart of a survival adventure set amidst the vast Pacific Ocean. Stranded on a deserted island, your mission is to gather resources, build shelters, and navigate the treacherous waters. Hunt for food, fell trees, and explore neighboring islands teeming with unique treasures. The journey is perilous, but the rewards are breathtaking.\nAs a castaway, you’ll experience the raw beauty and harsh realities of island life. Bask in the sun on golden sands, swim through crystal-clear waters, and marvel at the breathtaking Pacific landscapes. However, the weather can turn treacherous, with torrential rains and thunderous storms. Be prepared to seek shelter and weather the elements\nTo survive, you’ll need to harness your ingenuity and use the natural resources around you. Hunt animals, gather wood, and scavenge abandoned ships to build a sturdy base. But remember, the isolation can take a toll on your sanity. Ensure you’re well-rested and vigilant, as unnatural apparitions may haunt your dreams and threaten your life. SCREENSHOTS SYSTEM REQUIREMENTS OS: Windows 10 Processor: Intel Core i3-6100 or equivalent CPU Memory: 8 GB RAM Graphics: NVIDIA GeForce GTX 970 or AMD equivalent Storage: 5 GB available space Additional Notes: Does not work well with integrated GPUs GAME INFO Genre: Action, Adventure, Casual, Early Access Developer: Mardonpol Inc. Platform: PC Game Size: 3 GB Released By: DRM-Free (Ty Lopsider for csf/cs.rin) Version : v0.1.48 | Early Access Pre-Installed Game GOFILE DOWNLOAD HERE MegaDB DOWNLOAD HERE Buzzheavier DOWNLOAD HERE",
    "screenshots": [
        "https://steamrip.com/wp-content/uploads/2024/09/project-castaway-steamrip.jpg",
        "https://steamrip.com/wp-content/uploads/2024/09/project-castaway-screenshots-steamrip.jpg"
    ],
    "system_requirements": {
        "OS": "Windows 10",
        "Processor": "Intel Core i3-6100 or equivalent CPU",
        "Memory": "8 GB RAM",
        "Graphics": "NVIDIA GeForce GTX 970 or AMD equivalent",
        "Storage": "5 GB available space",
        "Additional Notes": "Does not work well with integrated GPUs"
    },
    "game_info": {
        "Genre": "Action, Adventure, Casual, Early Access",
        "Developer": "Mardonpol Inc.",
        "Platform": "PC",
        "Game Size": "3 GB",
        "Released By": "DRM-Free (Ty Lopsider for csf/cs.rin)",
        "Version": "v0.1.48 | Early Access",
        "Pre-Installed Game": ""
    },
    "download_links": [
        "https://gofile.io/d/LmGH2M",
        "https://megadb.net/d9rqy19xuudo",
        "https://buzzheavier.com/x3je6d3ghpdk"
    ],
    "cover_image": "https://steamrip.com/wp-content/uploads/2024/09/project-castaway-preinstalled-steamrip.jpg"
}